hiten/__init__.py
hiten/algorithms/__init__.py
hiten/algorithms/bifurcation/__init__.py
hiten/algorithms/bifurcation/analysis.py
hiten/algorithms/bifurcation/base.py
hiten/algorithms/bifurcation/transforms.py
hiten/algorithms/bifurcation/_tests/test_bifurcation_analysis.py
hiten/algorithms/bifurcation/_tests/test_bifurcation_base.py
hiten/algorithms/bifurcation/_tests/test_bifurcation_transforms.py
hiten/algorithms/common/__init__.py
hiten/algorithms/common/energy.py
hiten/algorithms/connections/__init__.py
hiten/algorithms/connections/backends.py
hiten/algorithms/connections/base.py
hiten/algorithms/connections/config.py
hiten/algorithms/connections/engine.py
hiten/algorithms/connections/interfaces.py
hiten/algorithms/connections/options.py
hiten/algorithms/connections/types.py
hiten/algorithms/continuation/__init__.py
hiten/algorithms/continuation/base.py
hiten/algorithms/continuation/config.py
hiten/algorithms/continuation/interfaces.py
hiten/algorithms/continuation/operators.py
hiten/algorithms/continuation/options.py
hiten/algorithms/continuation/protocols.py
hiten/algorithms/continuation/types.py
hiten/algorithms/continuation/backends/__init__.py
hiten/algorithms/continuation/backends/base.py
hiten/algorithms/continuation/backends/pc.py
hiten/algorithms/continuation/engine/__init__.py
hiten/algorithms/continuation/engine/base.py
hiten/algorithms/continuation/engine/engine.py
hiten/algorithms/continuation/stepping/__init__.py
hiten/algorithms/continuation/stepping/base.py
hiten/algorithms/continuation/stepping/plain.py
hiten/algorithms/continuation/stepping/support.py
hiten/algorithms/continuation/stepping/np/__init__.py
hiten/algorithms/continuation/stepping/np/base.py
hiten/algorithms/continuation/stepping/sc/__init__.py
hiten/algorithms/continuation/stepping/sc/base.py
hiten/algorithms/corrector/__init__.py
hiten/algorithms/corrector/base.py
hiten/algorithms/corrector/config.py
hiten/algorithms/corrector/interfaces.py
hiten/algorithms/corrector/operators.py
hiten-0.5.3.dist-info/licenses/LICENSE
hiten-0.5.3.dist-info/METADATA
hiten-0.5.3.dist-info/WHEEL
hiten-0.5.3.dist-info/top_level.txt
hiten-0.5.3.dist-info/RECORD
