Metadata-Version: 2.4
Name: hiten
Version: 0.5.3
Summary: HITEN - Computational Toolkit for the Circular Restricted Three-Body Problem
Author-email: Gad Marconi <gad.marconi@cranfield.ac.uk>
License-Expression: MIT
Project-URL: Homepage, https://github.com/iamgadmarconi/hiten
Project-URL: Bug Tracker, https://github.com/iamgadmarconi/hiten/issues
Requires-Python: >=3.9
License-File: LICENSE
Requires-Dist: numpy>=1.23
Requires-Dist: scipy>=1.15
Requires-Dist: numba>=0.61
Requires-Dist: mpmath>=1.3
Requires-Dist: sympy>=1.14
Requires-Dist: h5py>=3.13
Requires-Dist: matplotlib>=3.7.0
Requires-Dist: tqdm>=4.67
Requires-Dist: pandas>=2.3.0
Provides-Extra: dev
Requires-Dist: pytest>=8; extra == "dev"
Requires-Dist: black>=24; extra == "dev"
Requires-Dist: ruff>=0.3; extra == "dev"
Provides-Extra: docs
Requires-Dist: sphinx>=7.0; extra == "docs"
Requires-Dist: sphinx-rtd-theme>=1.3; extra == "docs"
Requires-Dist: myst-parser>=2.0; extra == "docs"
Requires-Dist: sphinx-autodoc-typehints>=1.24; extra == "docs"
Dynamic: license-file
